odoo8_addon_framework_agreement_sourcing-8.0.2.0.0-py2.7-nspkg.pth
odoo8_addon_framework_agreement_sourcing-8.0.2.0.0.dist-info/top_level.txt
odoo8_addon_framework_agreement_sourcing-8.0.2.0.0.dist-info/WHEEL
odoo8_addon_framework_agreement_sourcing-8.0.2.0.0.dist-info/RECORD
odoo8_addon_framework_agreement_sourcing-8.0.2.0.0.dist-info/metadata.json
odoo8_addon_framework_agreement_sourcing-8.0.2.0.0.dist-info/DESCRIPTION.rst
odoo8_addon_framework_agreement_sourcing-8.0.2.0.0.dist-info/METADATA
odoo8_addon_framework_agreement_sourcing-8.0.2.0.0.dist-info/namespace_packages.txt
odoo_addons/framework_agreement_sourcing/__openerp__.py
odoo_addons/framework_agreement_sourcing/__init__.py
odoo_addons/framework_agreement_sourcing/README.rst
odoo_addons/framework_agreement_sourcing/view/requisition_view.xml
odoo_addons/framework_agreement_sourcing/i18n/framework_agreement_sourcing.pot
odoo_addons/framework_agreement_sourcing/i18n/en_US.po
odoo_addons/framework_agreement_sourcing/model/purchase.py
odoo_addons/framework_agreement_sourcing/model/logistic_requisition.py
odoo_addons/framework_agreement_sourcing/model/sale_order.py
odoo_addons/framework_agreement_sourcing/model/logistic_requisition_source.py
odoo_addons/framework_agreement_sourcing/model/__init__.py
odoo_addons/framework_agreement_sourcing/wizard/cost_estimate.py
odoo_addons/framework_agreement_sourcing/wizard/__init__.py
odoo_addons/framework_agreement_sourcing/wizard/logistic_requisition_source_create_po.py
odoo_addons/framework_agreement_sourcing/wizard/logistic_requisition_source_create_po_view.xml
odoo_addons/framework_agreement_sourcing/tests/test_generate_source.py
odoo_addons/framework_agreement_sourcing/tests/test_agreement_source_line_to_po.py
odoo_addons/framework_agreement_sourcing/tests/__init__.py
odoo_addons/framework_agreement_sourcing/tests/common.py
odoo_addons/framework_agreement_sourcing/tests/test_check_sourcing.py
