Metadata-Version: 2.0
Name: odoo8-addon-framework-agreement-sourcing
Version: 8.0.2.0.0
Summary: Sourcing with Framework Agreements
Home-page: http://www.camptocamp.com
Author: UNKNOWN
Author-email: UNKNOWN
License: AGPL-3
Platform: UNKNOWN
Requires-Dist: odoo (<9.0a,>=8.0a)
Requires-Dist: odoo8-addon-framework-agreement
Requires-Dist: odoo8-addon-logistic-requisition
Classifier: Programming Language :: Python :: 2.7
Classifier: Framework :: Odoo
Classifier: License :: OSI Approved :: GNU Affero General Public License v3
